hello_pypi/__init__.py
hello_pypi/hello.py
hackhan_hello-0.0.6.dist-info/LICENSE
hackhan_hello-0.0.6.dist-info/METADATA
hackhan_hello-0.0.6.dist-info/WHEEL
hackhan_hello-0.0.6.dist-info/top_level.txt
hackhan_hello-0.0.6.dist-info/RECORD
